yaaredis/__init__.py
yaaredis/cache.py
yaaredis/client.py
yaaredis/commands/__init__.py
yaaredis/commands/cluster.py
yaaredis/commands/connection.py
yaaredis/commands/extra.py
yaaredis/commands/geo.py
yaaredis/commands/hash.py
yaaredis/commands/hyperlog.py
yaaredis/commands/iter.py
yaaredis/commands/keys.py
yaaredis/commands/lists.py
yaaredis/commands/pubsub.py
yaaredis/commands/scripting.py
yaaredis/commands/sentinel.py
yaaredis/commands/server.py
yaaredis/commands/sets.py
yaaredis/commands/sorted_set.py
yaaredis/commands/streams.py
yaaredis/commands/strings.py
yaaredis/commands/transaction.py
yaaredis/compat.py
yaaredis/connection.py
yaaredis/exceptions.py
yaaredis/lock.py
yaaredis/nodemanager.py
yaaredis/pipeline.py
yaaredis/pool.py
yaaredis/pubsub.py
yaaredis/scripting.py
yaaredis/sentinel.py
yaaredis/speedups.c
yaaredis/speedups.pyi
yaaredis/utils.py
yaaredis/speedups.cpython-39-darwin.so
yaaredis-3.0.0.dist-info/LICENSE
yaaredis-3.0.0.dist-info/WHEEL
yaaredis-3.0.0.dist-info/METADATA
yaaredis-3.0.0.dist-info/RECORD
