Metadata-Version: 2.1
Name: yaaredis
Version: 3.0.0
Summary: Python async client for Redis key-value store
Home-page: https://github.com/talkiq/yaaredis
License: MIT
Author: Vi Engineering
Author-email: voiceai-eng@dialpad.com
Requires-Python: >=3.6,<4.0
Classifier: License :: OSI Approved :: MIT License
Classifier: Programming Language :: Python :: 3
Classifier: Programming Language :: Python :: 3.10
Classifier: Programming Language :: Python :: 3.6
Classifier: Programming Language :: Python :: 3.7
Classifier: Programming Language :: Python :: 3.8
Classifier: Programming Language :: Python :: 3.9
Provides-Extra: hiredis
Requires-Dist: contextvars (>=1.0.0,<3.0.0); python_version < "3.7"
Requires-Dist: hiredis (>=0.2.0,<3.0.0); extra == "hiredis"
Project-URL: Repository, https://github.com/talkiq/yaaredis
